fwtv/__init__.py
fwtv/main.py
fwtv/verifier.py
fwtv/objects/__init__.py
fwtv/objects/async_converter.py
fwtv/widgets/__init__.py
fwtv/widgets/login_widget.py
fwtv/widgets/settings_widget.py
fwtv/widgets/table_widget.py
fwtv/widgets/working_time_widget.py
fwtv-2.4.1.dist-info/METADATA
fwtv-2.4.1.dist-info/WHEEL
fwtv-2.4.1.dist-info/entry_points.txt
fwtv-2.4.1.dist-info/licenses/LICENSE
fwtv-2.4.1.dist-info/RECORD
