Metadata-Version: 2.4
Name: fwtv
Version: 2.4.1
Summary: Verification that attendances comply with german rules. Also provide an integration to the api of FactorialHR
Project-URL: Homepage, https://github.com/leon1995/fwtv
Project-URL: Bug Tracker, https://github.com/leon1995/fwtv/issues
Project-URL: Changelog, https://github.com/leon1995/fwtv/blob/main/CHANGELOG.md
Project-URL: Repository, https://github.com/leon1995/fwtv.git
Author-email: Leon Budnick <y6q6ea9w@mail-proxy.org>
License-File: LICENSE
Keywords: FactorialHR,HR,Working time
Classifier: Development Status :: 5 - Production/Stable
Classifier: Intended Audience :: Developers
Classifier: Intended Audience :: End Users/Desktop
Classifier: License :: OSI Approved :: GNU Affero General Public License v3
Classifier: Operating System :: OS Independent
Classifier: Programming Language :: Python :: 3
Classifier: Programming Language :: Python :: 3.11
Classifier: Programming Language :: Python :: 3.12
Classifier: Programming Language :: Python :: 3.13
Classifier: Topic :: Office/Business
Requires-Python: <3.14,>=3.11
Requires-Dist: aiohttp>=3.11.13
Requires-Dist: factorialhr==4.0.0b3
Requires-Dist: outcome>=1.3.0.post0
Requires-Dist: pyside6-essentials>=6.8.2.1
Requires-Dist: tabulate>=0.9.0
Requires-Dist: trio>=0.29.0
